<annotation>
	<folder>malignant</folder>
	<filename>malignant (20).png</filename>
	<path>/Users/abhinav/Desktop/Breast Cancer classification/Data/malignant/malignant (20).png</path>
	<source>
		<database>Unknown</database>
	</source>
	<size>
		<width>558</width>
		<height>475</height>
		<depth>1</depth>
	</size>
	<segmented>0</segmented>
	<object>
		<name>malignant</name>
		<pose>Unspecified</pose>
		<truncated>0</truncated>
		<difficult>0</difficult>
		<bndbox>
			<xmin>83</xmin>
			<ymin>122</ymin>
			<xmax>395</xmax>
			<ymax>372</ymax>
		</bndbox>
	</object>
</annotation>
